cfmtoolbox_hello_world/__init__.py
cfmtoolbox_hello_world-0.1.0.dist-info/METADATA
cfmtoolbox_hello_world-0.1.0.dist-info/WHEEL
cfmtoolbox_hello_world-0.1.0.dist-info/entry_points.txt
cfmtoolbox_hello_world-0.1.0.dist-info/RECORD
